takopi/__init__.py
takopi/api.py
takopi/backends.py
takopi/backends_helpers.py
takopi/cli/__init__.py
takopi/cli/config.py
takopi/cli/doctor.py
takopi/cli/init.py
takopi/cli/onboarding_cmd.py
takopi/cli/plugins.py
takopi/cli/run.py
takopi/commands.py
takopi/config.py
takopi/config_migrations.py
takopi/config_watch.py
takopi/context.py
takopi/directives.py
takopi/engines.py
takopi/events.py
takopi/ids.py
takopi/lockfile.py
takopi/logging.py
takopi/markdown.py
takopi/model.py
takopi/plugins.py
takopi/presenter.py
takopi/progress.py
takopi/router.py
takopi/runner.py
takopi/runner_bridge.py
takopi/runners/__init__.py
takopi/runners/claude.py
takopi/runners/codex.py
takopi/runners/mock.py
takopi/runners/opencode.py
takopi/runners/pi.py
takopi/runners/run_options.py
takopi/runners/tool_actions.py
takopi/runtime_loader.py
takopi/scheduler.py
takopi/schemas/__init__.py
takopi/schemas/claude.py
takopi/schemas/codex.py
takopi/schemas/opencode.py
takopi/schemas/pi.py
takopi/settings.py
takopi/telegram/__init__.py
takopi/telegram/api_models.py
takopi/telegram/api_schemas.py
takopi/telegram/backend.py
takopi/telegram/bridge.py
takopi/telegram/chat_prefs.py
takopi/telegram/chat_sessions.py
takopi/telegram/client.py
takopi/telegram/client_api.py
takopi/telegram/commands/__init__.py
takopi/telegram/commands/agent.py
takopi/telegram/commands/cancel.py
takopi/telegram/commands/dispatch.py
takopi/telegram/commands/executor.py
takopi/telegram/commands/file_transfer.py
takopi/telegram/commands/handlers.py
takopi/telegram/commands/media.py
takopi/telegram/commands/menu.py
takopi/telegram/commands/model.py
takopi/telegram/commands/overrides.py
takopi/telegram/commands/parse.py
takopi/telegram/commands/plan.py
takopi/telegram/commands/reasoning.py
takopi/telegram/commands/reply.py
takopi/telegram/commands/topics.py
takopi/telegram/commands/trigger.py
takopi/telegram/context.py
takopi/telegram/engine_defaults.py
takopi/telegram/engine_overrides.py
takopi/telegram/files.py
takopi-0.21.4.dist-info/WHEEL
takopi-0.21.4.dist-info/entry_points.txt
takopi-0.21.4.dist-info/METADATA
takopi-0.21.4.dist-info/RECORD
